{
  "kind": "singleType",
  "collectionName": "configurations",
  "info": {
    "singularName": "configuration",
    "pluralName": "configurations",
    "displayName": "Configuration",
    "description": ""
  },
  "options": {
    "draftAndPublish": true
  },
  "pluginOptions": {},
  "attributes": {
    "popup": {
      "type": "boolean",
      "default": false
    },
    "enrolledstudents": {
      "type": "boolean",
      "default": false
    },
    "emailDocument": {
      "type": "media",
      "multiple": false,
      "required": false,
      "allowedTypes": [
        "images",
        "files",
        "videos",
        "audios"
      ]
    },
    "coupons": {
      "type": "component",
      "repeatable": false,
      "component": "coupons.coupons"
    },
    "tax": {
      "type": "integer"
    },
    "documentEmailSubject": {
      "type": "string"
    },
    "documentEmailMessage": {
      "type": "richtext"
    },
    "offerEmailSubject": {
      "type": "string"
    },
    "offerEmailMessage": {
      "type": "richtext"
    },
    "testEmail": {
      "type": "text"
    }
  }
}
